ef/__init__.py
ef-0.0.6.dist-info/licenses/LICENSE
ef-0.0.6.dist-info/METADATA
ef-0.0.6.dist-info/WHEEL
ef-0.0.6.dist-info/top_level.txt
ef-0.0.6.dist-info/RECORD
