Metadata-Version: 2.4
Name: ef
Version: 0.0.6
Summary: An example of connecting the flush of one buffer to the push of another.
Home-page: https://github.com/t-c-w/ef
Author: Thor Whalen
License: apache-2.0
Platform: any
License-File: LICENSE
Dynamic: license-file
